LICENSE
pyproject.toml
queuing_hub/__init__.py
queuing_hub/forwarder.py
queuing_hub/publisher.py
queuing_hub/subscriber.py
queuing_hub.egg-info/PKG-INFO
queuing_hub.egg-info/SOURCES.txt
queuing_hub.egg-info/dependency_links.txt
queuing_hub.egg-info/requires.txt
queuing_hub.egg-info/top_level.txt
queuing_hub/conn/__init__.py
queuing_hub/conn/aws.py
queuing_hub/conn/base.py
queuing_hub/conn/gcp.py