Metadata-Version: 2.1
Name: queuing-hub
Version: 0.0.0
Summary: Multi-cloud Queuing Hub
Home-page: https://github.com/tosh223/py-queuing-hub
Author: Toshifumi Tsutsumi
License: UNKNOWN
Keywords: aws,gcp,queue,development
Platform: UNKNOWN
Classifier: Development Status :: 4 - Beta
Classifier: Intended Audience :: Developers
Classifier: Topic :: Software Development :: Libraries :: Python Modules
Classifier: License :: OSI Approved :: MIT License
Classifier: Programming Language :: Python :: 3 :: Only
Requires-Python: >=3.6, <3.10
